{
  "stopVoice": {
    "1.6.0": []
  },
  "pauseVoice": {
    "1.6.0": []
  },
  "playVoice": {
    "1.6.0": []
  },
  "createAudioContext": {
    "1.6.0": []
  },
  "stopRecord": {
    "1.6.0": []
  },
  "startRecord": {
    "1.6.0": []
  },
  "onBackgroundAudioStop": {
    "1.2.0": []
  },
  "onBackgroundAudioPause": {
    "1.2.0": []
  },
  "onBackgroundAudioPlay": {
    "1.2.0": []
  },
  "stopBackgroundAudio": {
    "1.2.0": []
  },
  "seekBackgroundAudio": {
    "1.2.0": []
  },
  "pauseBackgroundAudio": {
    "1.2.0": []
  },
  "playBackgroundAudio": {
    "1.2.0": []
  },
  "getBackgroundAudioPlayerState": {
    "1.2.0": []
  },
  "setTopBarText": {
    "1.9.9": []
  },
  "createContext": {
    "1.0.0": []
  },
  "drawCanvas": {
    "1.0.0": []
  },
  "createCanvasContext": {
    "1.0.0": [
      "getActions"
    ],
    "1.9.90": [
      {
        "$method": [
          "setFontSize",
          "setMiterLimit",
          "setLineDash",
          "setLineCap",
          "setLineJoin",
          "setLineWidth",
          "setGlobalAlpha",
          "setShadow",
          "setStrokeStyle",
          "setFillStyle"
        ]
      }
    ]
  }
}